validaus/__init__.py
validaus/validaus.py
validaus-0.1.6.dist-info/LICENSE
validaus-0.1.6.dist-info/METADATA
validaus-0.1.6.dist-info/WHEEL
validaus-0.1.6.dist-info/top_level.txt
validaus-0.1.6.dist-info/RECORD
