Metadata-Version: 2.1
Name: validaus
Version: 0.1.6
Summary: Validaus Python Module
Home-page: https://www.validaus.com
Author: Validaus Inc.
Author-email: support@validaus.com
License: MIT
Platform: UNKNOWN
Classifier: Programming Language :: Python :: 3
Classifier: License :: OSI Approved :: MIT License
Classifier: Operating System :: OS Independent
Requires-Python: >=3.6
License-File: LICENSE
Requires-Dist: requests
